
  {
    "name": "BALAJI V",
    "rollNo": "19DX03",
    "email": "19dx03@psgpolytech.ac.in",
    "address": "SRI KRISHNA NAGAR, TVR ROAD, PAPPAMMALPURAM, AUNDIPATTI-625512.",
    "marks": {
      "semester1": {
        "contiousAssement1": {
          "X18101 - ENGINEERING MATHEMATICS":8,
          "X18102 - PHYSICS":10,
          "X18103 - CHEMISTRY":7.5,
          "X18104 - ENGLISH":13,
          "Z18105 - BASICS ENGNEERING GRAPHICS":10
        },
        "contiousAssement2": {
          "X18101 - ENGINEERING MATHEMATICS":10,
          "X18102 - PHYSICS":9,
          "X18103 - CHEMISTRY":8,
          "X18104 - ENGLISH":13,
          "Z18105 - BASICS ENGNEERING GRAPHICS":10
        },
        "contiousAssement3": {
          "X18101 - ENGINEERING MATHEMATICS":11,
          "X18102 - PHYSICS":12,
          "X18103 - CHEMISTRY":10,
          "X18104 - ENGLISH":15,
          "Z18105 - BASICS ENGNEERING GRAPHICS":9
        },
        "practicalExamination": {
          "X18151 - PHYSICS LABORATARY":82,
          "X18152 - CHEMISTRY LABORATARY":89,
          "Z18153 - C PROGRAMMING":91
        },
        "examination": {
          "X18101 - ENGINEERING MATHEMATICS":78,
          "X18102 - PHYSICS":83,
          "X18103 - CHEMISTRY":70,
          "X18104 - ENGLISH":100,
          "Z18105 - BASICS ENGNEERING GRAPHICS":84
        },
        "others": {
          "X18154 - INPLANT TRANING":"P",
          "X18155 - PHYSICAL EDUCATION":"P"
        }
      },
      "semester2": {
        "contiousAssement1": {
          "X18201 - ENGINEERING MATHEMATICS 1":9,
          "X18202 - CALCULUS AND ITS APPLICATION":8,
          "Z18203 - APPLIED PHYSICS":11,
          "Z18204 - ENGINEERING CHEMISTRY":10,
          "Z18205 - PROBLEM SOLVING USING PYTHON":11
        },
        "contiousAssement2": {
          "X18201 - ENGINEERING MATHEMATICS 1":9,
          "X18202 - CALCULUS AND ITS APPLICATION":7,
          "Z18203 - APPLIED PHYSICS":8,
          "Z18204 - ENGINEERING CHEMISTRY":10,
          "Z18205 - PROBLEM SOLVING USING PYTHON":11
        },
        "contiousAssement3": {
          "X18201 - ENGINEERING MATHEMATICS 1":13,
          "X18202 - CALCULUS AND ITS APPLICATION":8,
          "Z18203 - APPLIED PHYSICS":11,
          "Z18204 - ENGINEERING CHEMISTRY":10,
          "Z18205 - PROBLEM SOLVING USING PYTHON":14
        },
        "practicalExamination": {
          "Z18251 - APPLIED PHYSICS LABORATARY":87,
          "X18252 - CHEMISTRY LABORATARY":88,
          "Z18253 - PROBLEM SOLVING USING PYTHON LABORATARY":95
        },
        "examination": {
          "X18201 - ENGINEERING MATHEMATICS 1":91,
          "X18202 - CALCULUS AND ITS APPLICATION":86,
          "Z18203 - APPLIED PHYSICS":90,
          "Z18204 - ENGINEERING CHEMISTRY":84,
          "Z18205 - PROBLEM SOLVING USING PYTHON":82
        },
        "others": {
          "X18254 - COMMUNICATIVE ENGLISH LABORATARY":"P",
          "X18255 - PHYSICAL EDUCATION 2":"P"
        }
      },
      "semester3": {
        "contiousAssement1": {
          "Z18301 - STATISTICS AND PROBABILITY MODELS":9,
          "Z18302 - BASICS OF ELECTRONICS":11,
          "Z18303 - RELATIONAL DATABASE MANAGEMENT SYSTEM":8,
          "Z18304 - DATA STRUCTURE":7.5
        },
        "contiousAssement2": {
          "Z18301 - STATISTICS AND PROBABILITY MODELS":8,
          "Z18302 - BASICS OF ELECTRONICS":9,
          "Z18303 - RELATIONAL DATABASE MANAGEMENT SYSTEM":13,
          "Z18304 - DATA STRUCTURE":11
        },
        "contiousAssement3": {
          "Z18301 - STATISTICS AND PROBABILITY MODELS":11,
          "Z18302 - BASICS OF ELECTRONICS":12,
          "Z18303 - RELATIONAL DATABASE MANAGEMENT SYSTEM":7.5,
          "Z18304 - DATA STRUCTURE":13
        },
        "practicalExamination": {
          "Z18351 - ELECTRONICS LABORATARY":81,
          "Z18352 - RELATIONAL DATABASE MANAGEMENT SYSTEM LABORATARY":77,
          "Z18353 - DATA STRUCTURE LABORATARY":84,
          "Z18354 - PC HARDWARE AND PERIPHERALS":85,
          "Z18355 - MULTIMEDIA LABORATARY":100
        },
        "examination": {
          "Z18301 - STATISTICS AND PROBABILITY MODELS":77,
          "Z18302 - BASICS OF ELECTRONICS":80,
          "Z18303 - RELATIONAL DATABASE MANAGEMENT SYSTEM":84,
          "Z18304 - DATA STRUCTURE":99
        },
        "others": {
          "NIL":null
        }
      },
      "semester4": {
        "contiousAssement1": {
          "Z18401 - JAVA PROGRAMMING":12,
          "Z18402 - OPERATING SYSTEM":13,
          "Z18403 - SOFTWARE ENGINEERING":11,
          "Z18404 - MICROPROCESSOR AND MICROCONTROLLER":13
        },
        "contiousAssement2": {
          "Z18401 - JAVA PROGRAMMING":11,
          "Z18402 - OPERATING SYSTEM":12,
          "Z18403 - SOFTWARE ENGINEERING":10,
          "Z18404 - MICROPROCESSOR AND MICROCONTROLLER":14
        },
        "contiousAssement3": {
          "Z18401 - JAVA PROGRAMMING":12,
          "Z18402 - OPERATING SYSTEM":13,
          "Z18403 - SOFTWARE ENGINEERING":12,
          "Z18404 - MICROPROCESSOR AND MICROCONTROLLER":15
        },
        "practicalExamination": {
          "Z18451 - JAVA PROGRAMMING LABORATARY":89,
          "Z18452 - MICROPROCESSOR AND MICROCONTROLLER LABORATARY":100,
          "Z18453 - RESPONSIVE WEB DESIGN LABORATARY":92,
          "Z18454 - TECHNICAL COMMUNICATION LABORATARY":86
        },
        "examination": {
          "Z18401 - JAVA PROGRAMMING":83,
          "Z18402 - OPERATING SYSTEM":90,
          "Z18403 - SOFTWARE ENGINEERING":89,
          "Z18404 - MICROPROCESSOR AND MICROCONTROLLER":96
        },
        "others": {
          "Z18455 - INTERNSHIP":"P"
        }
      },
      "semester5": {
        "contiousAssement1": {
          "Z18501 - COMPUTER NETWORK":6,
          "Z18502 - INFORMATION SECURITY":9,
          "Z18E04 - CONTENT MANAGEMENT SYSTEM":7
        },
        "contiousAssement2": {
          "Z18501 - COMPUTER NETWORK":11,
          "Z18502 - INFORMATION SECURITY":13,
          "Z18E04 - CONTENT MANAGEMENT SYSTEM":10
        },
        "contiousAssement3": {
          "Z18501 - COMPUTER NETWORK":13,
          "Z18502 - INFORMATION SECURITY":10,
          "Z18E04 - CONTENT MANAGEMENT SYSTEM":15
        },
        "practicalExamination": {
          "Z18551 - COMPUTER NETWORK LABORATARY":76,
          "Z18552 - WEB TECHNOLOGY LABORATARY":100,
          "Z18553 - SMART DEVICE PROGRAMMING LABORATARY":79,
          "Z18554 - ETHICAL HACKING AND PENETRATION TESTING LABORATARY":88
        },
        "examination": {
          "Z18501 - COMPUTER NETWORK":90,
          "Z18502 - INFORMATION SECURITY":80,
          "Z18E04 - CONTENT MANAGEMENT SYSTEM":99
        },
        "others": {
          "Z18555 - MINI PROJECT AND ENTREPRENEURSHIP":"P"
        }
      },
      "semester6": {
        "contiousAssement1": {
          "Z18601 - CLOUD COMPUTING":8,
          "Z18602 - BUILDING INTERNET OF THINGS":8.5,
          "Z18E00 - ELECTIVE THEORY":10
        },
        "contiousAssement2": {
          "Z18601 - CLOUD COMPUTING":11,
          "Z18602 - BUILDING INTERNET OF THINGS":10,
          "Z18E00 - ELECTIVE THEORY":8
        },
        "contiousAssement3": {
          "Z18601 - CLOUD COMPUTING":12,
          "Z18602 - BUILDING INTERNET OF THINGS":13,
          "Z18E00 - ELECTIVE THEORY":15
        },
        "practicalExamination": {
          "Z18651 - INTERNET OF THINGS":75,
          "Z18652 - SOFTWARE TESTING LABORATARY":90,
          "Z18653 - SERVER ADMINISTRATION LABORATARY":100,
          "Z18654 - ENTERPRISE COMPUTING LABORATARY":100
        },
        "examination": {
          "Z18601 - CLOUD COMPUTING":90,
          "Z18602 - BUILDING INTERNET OF THINGS":71,
          "Z18E00 - ELECTIVE THEORY":76
        },
        "others": {
          "Z18655 - PROJECT WORK VIVA VOICE":"P"
        }
      }
    }
  }
